AMcomandPack/__init__.py
AMcomandPack/geo/__init__.py
AMcomandPack/geo/tk.py
AMcomandPack/geo/extensions/Xmas.py
AMcomandPack/geo/extensions/__init__.py
AMcomandPack/geo/extensions/extensionFiles.py
AMcomandPack/geo/extensions/images/Xmas/XmasTree0.png
AMcomandPack/geo/extensions/images/Xmas/present0.png
AMcomandPack/geo/extensions/images/Xmas/present1.png
AMcomandPack/geo/extensions/images/Xmas/snowFlake0.png
AMcomandPack-0.0.0.2.2.1.dist-info/METADATA
AMcomandPack-0.0.0.2.2.1.dist-info/WHEEL
AMcomandPack-0.0.0.2.2.1.dist-info/top_level.txt
AMcomandPack-0.0.0.2.2.1.dist-info/RECORD
